phonkersbase/__init__.py
phonkersbase/client.py
phonkersbase-0.2.0.dist-info/licenses/LICENSE
phonkersbase-0.2.0.dist-info/METADATA
phonkersbase-0.2.0.dist-info/WHEEL
phonkersbase-0.2.0.dist-info/top_level.txt
phonkersbase-0.2.0.dist-info/RECORD
