Metadata-Version: 2.4
Name: phonkersbase
Version: 0.2.0
Summary: A Python client for the PhonkersBase API
Home-page: https://github.com/brokenbyteofcode/phonkersbase-py
Author: brokenbyteofcode
Author-email: BrokenByteOfCode <your.email@example.com>
License: MIT
Project-URL: Homepage, https://github.com/BrokenByteOfCode/phonkersbase-py
Project-URL: Repository, https://github.com/BrokenByteOfCode/phonkersbase-py
Project-URL: Documentation, https://github.com/BrokenByteOfCode/phonkersbase-py#readme
Classifier: Development Status :: 4 - Beta
Classifier: Intended Audience :: Developers
Classifier: License :: OSI Approved :: MIT License
Classifier: Operating System :: OS Independent
Classifier: Programming Language :: Python :: 3
Classifier: Programming Language :: Python :: 3.7
Classifier: Programming Language :: Python :: 3.8
Classifier: Programming Language :: Python :: 3.9
Classifier: Programming Language :: Python :: 3.10
Classifier: Programming Language :: Python :: 3.11
Requires-Python: >=3.7
License-File: LICENSE
Requires-Dist: requests>=2.25.0
Requires-Dist: cachetools>=4.2.0
Provides-Extra: dev
Requires-Dist: pytest>=6.0.0; extra == "dev"
Requires-Dist: pytest-cov>=2.10.0; extra == "dev"
Requires-Dist: black>=20.8b1; extra == "dev"
Requires-Dist: isort>=5.0.0; extra == "dev"
Requires-Dist: mypy>=0.800; extra == "dev"
Requires-Dist: twine>=3.4.1; extra == "dev"
Requires-Dist: build>=0.7.0; extra == "dev"
Dynamic: author
Dynamic: home-page
Dynamic: license-file
Dynamic: requires-python
